[
    {
        "title": "Web-development day one",
        "blogs": "Today we will be discussing how to build a full stack web application.",
        "user_id": 1
    },
    {
        "title": "Drone flight start",
        "blogs": "On this blog we will discuss my prefered brand of drones.",
        "user_id": 2
    },
    {
        "title": "Pc builder blog",
        "blogs": "Here I will be groing thrugh a blog entry of how to build a personal pc.",
        "user_id": 3
    },
    {
        "title": "Robotics Programmer",
        "blogs": "Hi, today I really want to spend some time talking about robotics and how we can program commands.",
        "user_id": 4
    }
]